cumulus_library_data_metrics/__init__.py
cumulus_library_data_metrics/attachment_utils.jinja
cumulus_library_data_metrics/base.py
cumulus_library_data_metrics/base.summary.jinja
cumulus_library_data_metrics/db_utils.jinja
cumulus_library_data_metrics/gen_prefix.py
cumulus_library_data_metrics/manifest.toml
cumulus_library_data_metrics/resource_info.py
cumulus_library_data_metrics/systems.py
cumulus_library_data_metrics/utils.jinja
cumulus_library_data_metrics/c_attachment_count/README.md
cumulus_library_data_metrics/c_attachment_count/c_attachment_count.jinja
cumulus_library_data_metrics/c_attachment_count/c_attachment_count.py
cumulus_library_data_metrics/c_content_type_use/README.md
cumulus_library_data_metrics/c_content_type_use/c_content_type_use.jinja
cumulus_library_data_metrics/c_content_type_use/c_content_type_use.py
cumulus_library_data_metrics/c_pt_count/README.md
cumulus_library_data_metrics/c_pt_count/c_pt_count.jinja
cumulus_library_data_metrics/c_pt_count/c_pt_count.py
cumulus_library_data_metrics/c_pt_deceased_count/README.md
cumulus_library_data_metrics/c_pt_deceased_count/c_pt_deceased_count.jinja
cumulus_library_data_metrics/c_pt_deceased_count/c_pt_deceased_count.py
cumulus_library_data_metrics/c_resource_count/README.md
cumulus_library_data_metrics/c_resource_count/c_resource_count.jinja
cumulus_library_data_metrics/c_resource_count/c_resource_count.py
cumulus_library_data_metrics/c_resources_per_pt/README.md
cumulus_library_data_metrics/c_resources_per_pt/c_resources_per_pt.jinja
cumulus_library_data_metrics/c_resources_per_pt/c_resources_per_pt.py
cumulus_library_data_metrics/c_system_use/README.md
cumulus_library_data_metrics/c_system_use/c_system_use.jinja
cumulus_library_data_metrics/c_system_use/c_system_use.py
cumulus_library_data_metrics/c_us_core_v6_count/README.md
cumulus_library_data_metrics/c_us_core_v6_count/c_us_core_v6_count.py
cumulus_library_data_metrics/c_us_core_v6_count/mandatory.jinja
cumulus_library_data_metrics-9.0.0.dist-info/licenses/LICENSE
cumulus_library_data_metrics-9.0.0.dist-info/WHEEL
cumulus_library_data_metrics-9.0.0.dist-info/METADATA
cumulus_library_data_metrics-9.0.0.dist-info/RECORD
