Metadata-Version: 2.4
Name: cumulus-library-data-metrics
Version: 9.0.0
Summary: Data quality and characterization metrics for Cumulus
Requires-Python: >= 3.11
License-Expression: Apache-2.0
Classifier: Operating System :: OS Independent
Classifier: Programming Language :: Python :: 3
Classifier: Topic :: Software Development :: Libraries :: Python Modules
License-File: LICENSE
Requires-Dist: cumulus-library >= 5, < 7
Requires-Dist: pre-commit ; extra == "dev"
Requires-Dist: ruff < 0.15 ; extra == "dev"
Requires-Dist: ddt ; extra == "tests"
Requires-Dist: pytest ; extra == "tests"
Project-URL: Documentation, https://docs.smarthealthit.org/cumulus/
Project-URL: Home, https://smarthealthit.org/cumulus/
Project-URL: Source, https://github.com/smart-on-fhir/cumulus-library-data-metrics
Provides-Extra: dev
Provides-Extra: tests
